{
  "content_lan": "일본어",
  "content_code": 4718,
  "content_name": "합격하길 바래! JLPT 실전모의고사 N3",
  "content_sample": "1",
  "content_chasi": "21",
  "content_size": "1000*650",
  "content_cm": "한정현",
  "content_data": [
    {
      "chasi": 1,
      "title_a": "실전모의고사 1회 - 언어지식(1)",
      "title_b": null,
      "page_name": [
        "인트로",
        "오늘의 강의"
      ],
      "mp4_bind_path": "X:/Darakwon Dropbox/윤인준/content/4718/mp4/a1_01h.mp4",
      "mp4_bind_time": "",
      "mp4_bind_path_500k": "X:/Darakwon Dropbox/윤인준/content/4718/mobile/a1_01h_500k.mp4",
      "mp4_bind_time_500k": ""
    },
    {
      "chasi": 2,
      "title_a": "실전모의고사 1회 - 언어지식(2), 독해(1)",
      "title_b": null,
      "page_name": [
        "인트로",
        "오늘의 강의"
      ],
      "mp4_bind_path": "X:/Darakwon Dropbox/윤인준/content/4718/mp4/a1_02h.mp4",
      "mp4_bind_time": "",
      "mp4_bind_path_500k": "X:/Darakwon Dropbox/윤인준/content/4718/mobile/a1_02h_500k.mp4",
      "mp4_bind_time_500k": ""
    },
    {
      "chasi": 3,
      "title_a": "실전모의고사 1회 - 독해(2)",
      "title_b": null,
      "page_name": [
        "인트로",
        "오늘의 강의"
      ],
      "mp4_bind_path": "X:/Darakwon Dropbox/윤인준/content/4718/mp4/a1_03h.mp4",
      "mp4_bind_time": "",
      "mp4_bind_path_500k": "X:/Darakwon Dropbox/윤인준/content/4718/mobile/a1_03h_500k.mp4",
      "mp4_bind_time_500k": ""
    },
    {
      "chasi": 4,
      "title_a": "실전모의고사 1회 - 독해(3)",
      "title_b": null,
      "page_name": [
        "인트로",
        "오늘의 강의"
      ],
      "mp4_bind_path": "X:/Darakwon Dropbox/윤인준/content/4718/mp4/a1_04h.mp4",
      "mp4_bind_time": "",
      "mp4_bind_path_500k": "X:/Darakwon Dropbox/윤인준/content/4718/mobile/a1_04h_500k.mp4",
      "mp4_bind_time_500k": ""
    },
    {
      "chasi": 5,
      "title_a": "실전모의고사 1회 - 청해(1)",
      "title_b": null,
      "page_name": [
        "인트로",
        "오늘의 강의"
      ],
      "mp4_bind_path": "X:/Darakwon Dropbox/윤인준/content/4718/mp4/a1_05h.mp4",
      "mp4_bind_time": "",
      "mp4_bind_path_500k": "X:/Darakwon Dropbox/윤인준/content/4718/mobile/a1_05h_500k.mp4",
      "mp4_bind_time_500k": ""
    },
    {
      "chasi": 6,
      "title_a": "실전모의고사 1회 - 청해(2)",
      "title_b": null,
      "page_name": [
        "인트로",
        "오늘의 강의"
      ],
      "mp4_bind_path": "X:/Darakwon Dropbox/윤인준/content/4718/mp4/a1_06h.mp4",
      "mp4_bind_time": "",
      "mp4_bind_path_500k": "X:/Darakwon Dropbox/윤인준/content/4718/mobile/a1_06h_500k.mp4",
      "mp4_bind_time_500k": ""
    },
    {
      "chasi": 7,
      "title_a": "실전모의고사 1회 - 청해(3)",
      "title_b": null,
      "page_name": [
        "인트로",
        "오늘의 강의"
      ],
      "mp4_bind_path": "X:/Darakwon Dropbox/윤인준/content/4718/mp4/a1_07h.mp4",
      "mp4_bind_time": "",
      "mp4_bind_path_500k": "X:/Darakwon Dropbox/윤인준/content/4718/mobile/a1_07h_500k.mp4",
      "mp4_bind_time_500k": ""
    },
    {
      "chasi": 8,
      "title_a": "실전모의고사 2회 - 언어지식(1)",
      "title_b": null,
      "page_name": [
        "인트로",
        "오늘의 강의"
      ],
      "mp4_bind_path": "X:/Darakwon Dropbox/윤인준/content/4718/mp4/a1_08h.mp4",
      "mp4_bind_time": "",
      "mp4_bind_path_500k": "X:/Darakwon Dropbox/윤인준/content/4718/mobile/a1_08h_500k.mp4",
      "mp4_bind_time_500k": ""
    },
    {
      "chasi": 9,
      "title_a": "실전모의고사 2회 - 언어지식(2), 독해(1)",
      "title_b": null,
      "page_name": [
        "인트로",
        "오늘의 강의"
      ],
      "mp4_bind_path": "X:/Darakwon Dropbox/윤인준/content/4718/mp4/a1_09h.mp4",
      "mp4_bind_time": "",
      "mp4_bind_path_500k": "X:/Darakwon Dropbox/윤인준/content/4718/mobile/a1_09h_500k.mp4",
      "mp4_bind_time_500k": ""
    },
    {
      "chasi": 10,
      "title_a": "실전모의고사 2회 - 독해(2)",
      "title_b": null,
      "page_name": [
        "인트로",
        "오늘의 강의"
      ],
      "mp4_bind_path": "X:/Darakwon Dropbox/윤인준/content/4718/mp4/a1_10h.mp4",
      "mp4_bind_time": "",
      "mp4_bind_path_500k": "X:/Darakwon Dropbox/윤인준/content/4718/mobile/a1_10h_500k.mp4",
      "mp4_bind_time_500k": ""
    },
    {
      "chasi": 11,
      "title_a": "실전모의고사 2회 - 독해(3)",
      "title_b": null,
      "page_name": [
        "인트로",
        "오늘의 강의"
      ],
      "mp4_bind_path": "X:/Darakwon Dropbox/윤인준/content/4718/mp4/a1_11h.mp4",
      "mp4_bind_time": "",
      "mp4_bind_path_500k": "X:/Darakwon Dropbox/윤인준/content/4718/mobile/a1_11h_500k.mp4",
      "mp4_bind_time_500k": ""
    },
    {
      "chasi": 12,
      "title_a": "실전모의고사 2회 - 청해(1)",
      "title_b": null,
      "page_name": [
        "인트로",
        "오늘의 강의"
      ],
      "mp4_bind_path": "X:/Darakwon Dropbox/윤인준/content/4718/mp4/a1_12h.mp4",
      "mp4_bind_time": "",
      "mp4_bind_path_500k": "X:/Darakwon Dropbox/윤인준/content/4718/mobile/a1_12h_500k.mp4",
      "mp4_bind_time_500k": ""
    },
    {
      "chasi": 13,
      "title_a": "실전모의고사 2회 - 청해(2)",
      "title_b": null,
      "page_name": [
        "인트로",
        "오늘의 강의"
      ],
      "mp4_bind_path": "X:/Darakwon Dropbox/윤인준/content/4718/mp4/a1_13h.mp4",
      "mp4_bind_time": "",
      "mp4_bind_path_500k": "X:/Darakwon Dropbox/윤인준/content/4718/mobile/a1_13h_500k.mp4",
      "mp4_bind_time_500k": ""
    },
    {
      "chasi": 14,
      "title_a": "실전모의고사 2회 - 청해(3)",
      "title_b": null,
      "page_name": [
        "인트로",
        "오늘의 강의"
      ],
      "mp4_bind_path": "X:/Darakwon Dropbox/윤인준/content/4718/mp4/a1_14h.mp4",
      "mp4_bind_time": "",
      "mp4_bind_path_500k": "X:/Darakwon Dropbox/윤인준/content/4718/mobile/a1_14h_500k.mp4",
      "mp4_bind_time_500k": ""
    },
    {
      "chasi": 15,
      "title_a": "실전모의고사 3회 - 언어지식(1)",
      "title_b": null,
      "page_name": [
        "인트로",
        "오늘의 강의"
      ],
      "mp4_bind_path": "X:/Darakwon Dropbox/윤인준/content/4718/mp4/a1_15h.mp4",
      "mp4_bind_time": "",
      "mp4_bind_path_500k": "X:/Darakwon Dropbox/윤인준/content/4718/mobile/a1_15h_500k.mp4",
      "mp4_bind_time_500k": ""
    },
    {
      "chasi": 16,
      "title_a": "실전모의고사 3회 - 언어지식(2), 독해(1)",
      "title_b": null,
      "page_name": [
        "인트로",
        "오늘의 강의"
      ],
      "mp4_bind_path": "X:/Darakwon Dropbox/윤인준/content/4718/mp4/a1_16h.mp4",
      "mp4_bind_time": "",
      "mp4_bind_path_500k": "X:/Darakwon Dropbox/윤인준/content/4718/mobile/a1_16h_500k.mp4",
      "mp4_bind_time_500k": ""
    },
    {
      "chasi": 17,
      "title_a": "실전모의고사 3회 - 독해(2)",
      "title_b": null,
      "page_name": [
        "인트로",
        "오늘의 강의"
      ],
      "mp4_bind_path": "X:/Darakwon Dropbox/윤인준/content/4718/mp4/a1_17h.mp4",
      "mp4_bind_time": "",
      "mp4_bind_path_500k": "X:/Darakwon Dropbox/윤인준/content/4718/mobile/a1_17h_500k.mp4",
      "mp4_bind_time_500k": ""
    },
    {
      "chasi": 18,
      "title_a": "실전모의고사 3회 - 독해(3)",
      "title_b": null,
      "page_name": [
        "인트로",
        "오늘의 강의"
      ],
      "mp4_bind_path": "X:/Darakwon Dropbox/윤인준/content/4718/mp4/a1_18h.mp4",
      "mp4_bind_time": "",
      "mp4_bind_path_500k": "X:/Darakwon Dropbox/윤인준/content/4718/mobile/a1_18h_500k.mp4",
      "mp4_bind_time_500k": ""
    },
    {
      "chasi": 19,
      "title_a": "실전모의고사 3회 - 청해(1)",
      "title_b": null,
      "page_name": [
        "인트로",
        "오늘의 강의"
      ],
      "mp4_bind_path": "X:/Darakwon Dropbox/윤인준/content/4718/mp4/a1_19h.mp4",
      "mp4_bind_time": "",
      "mp4_bind_path_500k": "X:/Darakwon Dropbox/윤인준/content/4718/mobile/a1_19h_500k.mp4",
      "mp4_bind_time_500k": ""
    },
    {
      "chasi": 20,
      "title_a": "실전모의고사 3회 - 청해(2)",
      "title_b": null,
      "page_name": [
        "인트로",
        "오늘의 강의"
      ],
      "mp4_bind_path": "X:/Darakwon Dropbox/윤인준/content/4718/mp4/a1_20h.mp4",
      "mp4_bind_time": "",
      "mp4_bind_path_500k": "X:/Darakwon Dropbox/윤인준/content/4718/mobile/a1_20h_500k.mp4",
      "mp4_bind_time_500k": ""
    },
    {
      "chasi": 21,
      "title_a": "실전모의고사 3회 - 청해(3)",
      "title_b": null,
      "page_name": [
        "인트로",
        "오늘의 강의"
      ],
      "mp4_bind_path": "X:/Darakwon Dropbox/윤인준/content/4718/mp4/a1_21h.mp4",
      "mp4_bind_time": "",
      "mp4_bind_path_500k": "X:/Darakwon Dropbox/윤인준/content/4718/mobile/a1_21h_500k.mp4",
      "mp4_bind_time_500k": ""
    }
  ]
}